fffio/__init__.py
fffio/frame_reader.py
fffio/frame_writer.py
fffio-0.7.0.dist-info/METADATA
fffio-0.7.0.dist-info/WHEEL
fffio-0.7.0.dist-info/licenses/LICENSE
fffio-0.7.0.dist-info/RECORD
