Metadata-Version: 2.4
Name: fffio
Version: 0.7.0
Summary: Python package of FFmpeg Frame Input/Output
License-Expression: MIT
License-File: LICENSE
Author: yamakox
Requires-Python: >=3.11
Classifier: Programming Language :: Python :: 3
Classifier: License :: OSI Approved :: MIT License
Classifier: Operating System :: OS Independent
Classifier: Development Status :: 4 - Beta
Requires-Dist: ffmpeg-python (>=0.2.0)
Requires-Dist: numpy (>=2.0.0)
Project-URL: Homepage, https://github.com/yamakox/fffio
Project-URL: Issues, https://github.com/yamakox/fffio/issues
